cloudmesh/inventory/__init__.py
cloudmesh/inventory/inventory.py
cloudmesh/inventory/command/__init__.py
cloudmesh/inventory/command/inventory.py
cloudmesh/inventory/etc/__init__.py
cloudmesh/inventory/schema/__init__.py
cloudmesh/inventory/schema/inventory.settings.py
cloudmesh_inventory-5.0.2.dist-info/LICENSE
cloudmesh_inventory-5.0.2.dist-info/METADATA
cloudmesh_inventory-5.0.2.dist-info/WHEEL
cloudmesh_inventory-5.0.2.dist-info/top_level.txt
cloudmesh_inventory-5.0.2.dist-info/RECORD
