Metadata-Version: 2.1
Name: cloudmesh-inventory
Version: 5.0.2
Summary: A cloudmesh command called inventory
Author-email: Gregor von Laszewski <laszewski@gmail.com>
Maintainer-email: Gregor von Laszewski <laszewski@gmail.com>
License: Apache License
Project-URL: Homepage, https://github.com/cloudmesh/cloudmesh-inventory
Project-URL: Documentation, https://github.com/cloudmesh/cloudmesh-inventory/blob/main/README.md
Project-URL: Repository, https://github.com/cloudmesh/cloudmesh-inventory.git
Project-URL: Issues, https://github.com/cloudmesh/cloudmesh-inventory/issues
Project-URL: Changelog, https://github.com/cloudmesh/cloudmesh-inventory/blob/main/CHANGELOG.md
Keywords: helper library,cloudmesh
Classifier: Development Status :: 5 - Production/Stable
Classifier: Environment :: Console
Classifier: Environment :: Other Environment
Classifier: Environment :: Plugins
Classifier: Intended Audience :: Information Technology
Classifier: Intended Audience :: Developers
Classifier: Intended Audience :: Education
Classifier: Intended Audience :: Science/Research
Classifier: Intended Audience :: System Administrators
Classifier: License :: OSI Approved :: Apache Software License
Classifier: Natural Language :: English
Classifier: Operating System :: OS Independent
Classifier: Operating System :: MacOS :: MacOS X
Classifier: Operating System :: POSIX :: Linux
Classifier: Operating System :: Microsoft :: Windows :: Windows 10
Classifier: Programming Language :: Python
Classifier: Programming Language :: Python :: 3
Classifier: Programming Language :: Python :: 3.12
Classifier: Topic :: Scientific/Engineering
Classifier: Topic :: Software Development :: Libraries
Classifier: Topic :: Software Development :: User Interfaces
Classifier: Topic :: System
Classifier: Topic :: System :: Distributed Computing
Classifier: Topic :: System :: Shells
Classifier: Topic :: Utilities
Requires-Python: >=3.8
License-File: LICENSE
Requires-Dist: toml
Requires-Dist: cloudmesh-cmd5
Requires-Dist: cloudmesh-configuration
